iso4217_money/__init__.py
iso4217_money/currency.py
iso4217_money/currency_formatting.py
iso4217_money/money.py
iso4217_money/resources/__init__.py
iso4217_money/resources/process_iso_4217_currencies.py
iso4217_money/statics.py
iso4217_money/types.py
iso4217_money/utils.py
iso4217_money-0.3.20250512.dist-info/LICENSE
iso4217_money-0.3.20250512.dist-info/METADATA
iso4217_money-0.3.20250512.dist-info/WHEEL
iso4217_money-0.3.20250512.dist-info/RECORD
