Metadata-Version: 2.3
Name: iso4217-money
Version: 0.3.20250512
Summary: 
License: The MIT License (MIT)
Keywords: ISO4217,Currency,Money
Author: Gonzalo Molpeceres Barrientos
Author-email: gonzalomolbar@gmail.com
Requires-Python: >=3.12
Classifier: Development Status :: 4 - Beta
Classifier: Intended Audience :: Developers
Classifier: License :: Other/Proprietary License
Classifier: Operating System :: OS Independent
Classifier: Programming Language :: Python :: 3
Classifier: Programming Language :: Python :: 3.12
Classifier: Programming Language :: Python :: 3.13
Project-URL: Repository, https://github.com/gonzalomolbar/ISO4217Money
